pyremoteplay/__init__.py
pyremoteplay/__main__.py
pyremoteplay/__version__.py
pyremoteplay/av.py
pyremoteplay/const.py
pyremoteplay/controller.py
pyremoteplay/crypt.py
pyremoteplay/ddp.py
pyremoteplay/device.py
pyremoteplay/errors.py
pyremoteplay/keys.py
pyremoteplay/oauth.py
pyremoteplay/profile.py
pyremoteplay/protobuf.py
pyremoteplay/register.py
pyremoteplay/session.py
pyremoteplay/socket.py
pyremoteplay/stream.py
pyremoteplay/stream_packets.py
pyremoteplay/takion_pb2.py
pyremoteplay/tracker.py
pyremoteplay/util.py
pyremoteplay/gamepad/__init__.py
pyremoteplay/gamepad/mapping.py
pyremoteplay/gui/__init__.py
pyremoteplay/gui/__main__.py
pyremoteplay/gui/audio.py
pyremoteplay/gui/controls.py
pyremoteplay/gui/device_grid.py
pyremoteplay/gui/joystick.py
pyremoteplay/gui/main_window.py
pyremoteplay/gui/options.py
pyremoteplay/gui/stream_window.py
pyremoteplay/gui/toolbar.py
pyremoteplay/gui/util.py
pyremoteplay/gui/video.py
pyremoteplay/gui/widgets.py
pyremoteplay/gui/workers.py
pyremoteplay/receiver/__init__.py
pyremoteplay-0.7.6.dist-info/LICENSE
pyremoteplay-0.7.6.dist-info/METADATA
pyremoteplay-0.7.6.dist-info/WHEEL
pyremoteplay-0.7.6.dist-info/entry_points.txt
pyremoteplay-0.7.6.dist-info/top_level.txt
pyremoteplay-0.7.6.dist-info/RECORD
