Metadata-Version: 2.1
Name: pyremoteplay
Version: 0.7.6
Summary: Remote Play Library and API
Home-page: https://github.com/ktnrg45/pyremoteplay
Author: ktnrg45
Author-email: ktnrg45dev@gmail.com
License: GPLv3
Keywords: playstation sony ps4 ps5 remote play remoteplay rp
Platform: UNKNOWN
Classifier: Development Status :: 4 - Beta
Classifier: Environment :: Console
Classifier: Environment :: Console :: Curses
Classifier: Environment :: X11 Applications :: Qt
Classifier: License :: OSI Approved :: GNU General Public License v3 (GPLv3)
Classifier: Natural Language :: English
Classifier: Operating System :: OS Independent
Classifier: Programming Language :: Python :: 3
Classifier: Programming Language :: Python :: 3.8
Classifier: Topic :: Games/Entertainment
Classifier: Topic :: Home Automation
Classifier: Topic :: Software Development :: Libraries :: Python Modules
Classifier: Topic :: System :: Hardware
Requires-Python: >=3.8
Provides-Extra: GUI
Provides-Extra: DEV
